[
  {
    "date": "2026-07-02T14:40:16.829Z",
    "status": "ok",
    "fixes": []
  },
  {
    "date": "2026-07-02T11:08:05.550Z",
    "status": "ok",
    "fixes": []
  },
  {
    "date": "2026-07-02T04:40:47.934Z",
    "status": "ok",
    "fixes": []
  },
  {
    "date": "2026-07-01T22:02:50.945Z",
    "status": "ok",
    "fixes": []
  },
  {
    "date": "2026-07-01T18:26:12.046Z",
    "status": "ok",
    "fixes": []
  },
  {
    "date": "2026-07-01T15:19:36.236Z",
    "status": "ok",
    "fixes": []
  },
  {
    "date": "2026-07-01T11:38:59.996Z",
    "status": "ok",
    "fixes": []
  },
  {
    "date": "2026-07-01T05:06:25.224Z",
    "status": "ok",
    "fixes": []
  },
  {
    "date": "2026-06-30T21:56:42.780Z",
    "status": "ok",
    "fixes": []
  },
  {
    "date": "2026-06-30T18:20:06.942Z",
    "status": "ok",
    "fixes": []
  },
  {
    "date": "2026-06-30T15:12:27.270Z",
    "status": "ok",
    "fixes": []
  },
  {
    "date": "2026-06-30T11:28:34.649Z",
    "status": "ok",
    "fixes": []
  },
  {
    "date": "2026-06-30T04:46:12.025Z",
    "status": "ok",
    "fixes": []
  },
  {
    "date": "2026-06-29T21:53:01.333Z",
    "status": "ok",
    "fixes": []
  },
  {
    "date": "2026-06-29T18:30:04.923Z",
    "status": "ok",
    "fixes": []
  },
  {
    "date": "2026-06-29T12:46:57.269Z",
    "status": "ok",
    "fixes": []
  }
]